wz_weather_utils/__about__.py
wz_weather_utils/__init__.py
wz_weather_utils/calc.py
wz_weather_utils/cma_connect.py
wz_weather_utils/grid_data.py
wz_weather_utils/lambert_data.py
wz_weather_utils/logging.py
wz_weather_utils/micaps.py
wz_weather_utils/open_scmoc.py
wz_weather_utils/read_yaml.py
wz_weather_utils/save_type.py
wz_weather_utils/wiz_sta01.py
wz_weather_utils/wizgrd.py
wz_weather_utils-0.0.2.dist-info/METADATA
wz_weather_utils-0.0.2.dist-info/WHEEL
wz_weather_utils-0.0.2.dist-info/licenses/LICENSE.txt
wz_weather_utils-0.0.2.dist-info/RECORD
